Workbook

Sheet Configuración
A1: PARÁMETROS DE CONFIGURACIÓN FINANCIERA Y TRIBUTARIA
A2: Variables globales de tasas horarias, impuestos (SUNAT Régimen MYPE), detracciones y pasarelas de pago.
A4: Concepto / Variable | B4: Valor | C4: Unidad | D4: Descripción
A5: Tasa Horaria Alberto (Costo MOD) | B5: 93.75 | C5: PEN/hora | D5: Tu valor por hora base para estimación interna ($25.00 * 3.75)
A6: Tasa Horaria Alberto (Venta) | B6: 150 | C6: PEN/hora | D6: Tu valor por hora cobrado para modificaciones/consultoría ($40.00 * 3.75)
A7: Tasa Horaria Junior (Costo MOD) | B7: 30 | C7: PEN/hora | D7: Tarifa horaria para programador junior de apoyo ($8.00 * 3.75)
A8: Tasa Horaria QA / Soporte (Costo MOD) | B8: 22.5 | C8: PEN/hora | D8: Tarifa horaria para asistente de pruebas de calidad ($6.00 * 3.75)
A9: Tipo de Cambio (TC) | B9: 3.75 | C9: Soles por USD | D9: Tipo de cambio oficial SUNAT promedio
A10: UIT Vigente | B10: 5150 | C10: Soles (PEN) | D10: Valor de la Unidad Impositiva Tributaria para el año fiscal
A11: Tasa de Detracción (Software) | B11: 0.12 | C11: Porcentaje | D11: Detracción obligatoria para servicios de software > S/. 700 (12%) - Código 022
A12: Tasa de IGV | B12: 0.18 | C12: Porcentaje | D12: Impuesto General a las Ventas aplicable en Perú (18%)
A13: RMT Pago a Cuenta Mensual | B13: 0.01 | C13: Porcentaje | D13: Régimen MYPE Tributario - Pago a cuenta de Renta mensual (1.0% para < 300 UIT)
A14: RMT Provisión Renta Anual | B14: 0.1 | C14: Porcentaje | D14: Tasa de regularización anual del RMT (10% hasta 15 UIT de utilidad)
A15: PayPal Comisión Fija | B15: 0.3 | C15: USD | D15: Tarifa transaccional fija de PayPal por pago internacional
A16: PayPal Comisión Porcentual | B16: 0.054 | C16: Porcentaje | D16: Comisión porcentual de PayPal por recepción internacional (5.4%)
... A19: Margen Comercial Objetivo | B19: 0.4 | C19: Porcentaje | D19: Margen comercial neto esperado sobre la venta sugerida (40%)

Sheet Overhead y Capacidad
A1: CAPACIDAD PRODUCTIVA Y PRORRATEO DE GASTOS INDIRECTOS (TDABC)
A2: Cálculo de horas facturables reales y costo del overhead mensual amortizado por hora.
A4: 1. Capacidad Laboral Facturable (TDABC)
A5: Métrica de Capacidad | B5: Valor | C5: Unidad | D5: Lógica / Referencia
A6: Días del Año | B6: 365 | C6: Días | D6: Año natural
A7: Fines de Semana | B7: 104 | C7: Días | D7: 52 fines de semana al año
A8: Feriados Nacionales (Perú) | B8: 16 | C8: Días | D8: Feriados oficiales calendario nacional
A9: Vacaciones / Descanso anual | B9: 15 | C9: Días | D9: Periodo de descanso proyectado para Alberto
A10: Días estimados de Enfermedad | B10: 5 | C10: Días | D10: Reserva de seguridad por imprevistos médicos
A11: Días Laborables Anuales | B11: =B6-B7-B8-B9-B10 | C11: Días | D11: Días laborables reales disponibles
A12: Horas Diarias Laborables | B12: 8 | C12: Horas | D12: Jornada estándar
A13: Tasa de Utilización Facturable | B13: 0.6 | C13: Porcentaje | D13: Porcentaje de tiempo dedicado a producir código facturable (60%)
A14: Horas Facturables Anuales | B14: =B11*B12*B13 | C14: Horas | D14: Horas útiles para proyectos facturables al año
A15: Horas Facturables Mensuales | B15: =B14/12 | C15: Horas | D15: Capacidad mensual real facturable promedio (90 horas)
A17: 2. Estructura de Gastos Fijos y Amortización Mensual (Soles PEN)
A18: Concepto / Gasto Fijo | B18: Costo Mensual | C18: Unidad | D18: Detalle de Prorrateo / Causalidad SUNAT
A19: VPS de Desarrollo (Hetzner Cloud) | B19: 225 | C19: S/. / mes | D19: Servidor de staging e integraciones propias ($60.00 USD)
A20: ChatGPT Plus / Claude Pro (Suscripción IA) | B20: 75 | C20: S/. / mes | D20: Suscripción para asistencia técnica y código ($20.00 USD)
A21: Google Workspace & One (Almacenamiento) | B21: 33.75 | C21: S/. / mes | D21: Correo corporativo y almacenamiento Drive ($9.00 USD)
A22: Asesoría Contable / Contador local | B22: 375 | C22: S/. / mes | D22: Servicios contables mensuales para la declaración RUC 10
A23: Servicios del Hogar (Prorrateo 50% internet/luz) | B23: 140 | C23: S/. / mes | D23: Deducción de luz (S/. 40), agua (S/. 30), internet (S/. 70) por oficina en casa
A24: Depreciación Laptop de Desarrollo (25% SUNAT) | B24: 75 | C24: S/. / mes | D24: Laptop de S/. 3,600 depreciada linealmente a 4 años contables
A25: Fondo de Ahorro para Laptop (Financiero) | B25: 75 | C25: S/. / mes | D25: Diferencial de fondo líquido para renovar equipo en 2 años reales
A26: Total Overhead Mensual (Gastos Generales) | B26: =SUM(B19:B25) | C26: S/. / mes | D26: Total costo indirecto a absorber por tus proyectos
A27: Tasa de Absorción de Costos Indirectos (TACI) | B27: =B26/B15 | C27: S/. por hora | D27: Costo indirecto por cada hora de desarrollo a facturar (Overhead/Horas)

Sheet Calculadora WBS
A1: COTIZADOR INTERACTIVO BASADO EN TAREAS (WBS / EDT)
A2: Escribe tus tareas de WBS, selecciona el rol (Alberto, Junior, QA) en la columna D y define las horas. Todo se calculará con fórmulas dinámicas.
A4: 1. ESTRUCTURA DE DESGLOSE DEL TRABAJO (WBS)
A5: ID | B5: Entregable / Fase | C5: Actividad del Software / IA | D5: Rol Responsable | E5: Horas | F5: Costo MOD/h | G5: Total MOD | H5: Tasa TACI | I5: Overhead CIF
A6: 1 | B6: Levantamiento y Diseño | C6: Reuniones de arquitectura y mockup UI/UX inicial | D6: Alberto | E6: 6 | F6: =IF(D6="Alberto", Configuración!$B$5, IF(D6="Junior", Configuración!$B$7, IF(D6="QA", Configuración!$B$8, 0))) | G6: =E6*F6 | H6: ='Overhead y Capacidad'!$B$27 | I6: =E6*H6
A7: 2 | B7: Desarrollo Frontend SPA | C7: Maquetación de pantallas en React/TS | D7: Junior | E7: 15 | F7: =IF(D7="Alberto", Configuración!$B$5, IF(D7="Junior", Configuración!$B$7, IF(D7="QA", Configuración!$B$8, 0))) | G7: =E7*F7 | H7: ='Overhead y Capacidad'!$B$27 | I7: =E7*H7
A8: 3 | B8: Integración de Base de Datos | C8: Creación de esquemas Postgres/MongoDB | D8: Junior | E8: 8 | F8: =IF(D8="Alberto", Configuración!$B$5, IF(D8="Junior", Configuración!$B$7, IF(D8="QA", Configuración!$B$8, 0))) | G8: =E8*F8 | H8: ='Overhead y Capacidad'!$B$27 | I8: =E8*H8
A9: 4 | B9: Desarrollo Backend API | C9: Orquestación de lógica en Node.js/Python | D9: Alberto | E9: 10 | F9: =IF(D9="Alberto", Configuración!$B$5, IF(D9="Junior", Configuración!$B$7, IF(D9="QA", Configuración!$B$8, 0))) | G9: =E9*F9 | H9: ='Overhead y Capacidad'!$B$27 | I9: =E9*H9
A10: 5 | B10: Integración Silhouette Brain | C10: Configuración de enjambres en n8n e IA | D10: Alberto | E10: 12 | F10: =IF(D10="Alberto", Configuración!$B$5, IF(D10="Junior", Configuración!$B$7, IF(D10="QA", Configuración!$B$8, 0))) | G10: =E10*F10 | H10: ='Overhead y Capacidad'!$B$27 | I10: =E10*H10
A11: 6 | B11: Conexión WhatsApp API | C11: Vinculación de webhook Meta Cloud API | D11: Junior | E11: 8 | F11: =IF(D11="Alberto", Configuración!$B$5, IF(D11="Junior", Configuración!$B$7, IF(D11="QA", Configuración!$B$8, 0))) | G11: =E11*F11 | H11: ='Overhead y Capacidad'!$B$27 | I11: =E11*H11
A12: 7 | B12: Pruebas de Calidad (QA) | C12: Testing de estrés y verificación de prompts | D12: QA | E12: 10 | F12: =IF(D12="Alberto", Configuración!$B$5, IF(D12="Junior", Configuración!$B$7, IF(D12="QA", Configuración!$B$8, 0))) | G12: =E12*F12 | H12: ='Overhead y Capacidad'!$B$27 | I12: =E12*H12
A13: 8 | B13: Despliegue y CI/CD | C13: Dockerización, pipelines y hosting en VPS | D13: Alberto | E13: 4 | F13: =IF(D13="Alberto", Configuración!$B$5, IF(D13="Junior", Configuración!$B$7, IF(D13="QA", Configuración!$B$8, 0))) | G13: =E13*F13 | H13: ='Overhead y Capacidad'!$B$27 | I13: =E13*H13
A14: 9 | B14: Documentación Técnica | C14: Manual operativo y video Loom | D14: Junior | E14: 4 | F14: =IF(D14="Alberto", Configuración!$B$5, IF(D14="Junior", Configuración!$B$7, IF(D14="QA", Configuración!$B$8, 0))) | G14: =E14*F14 | H14: ='Overhead y Capacidad'!$B$27 | I14: =E14*H14
A15: 10 | B15: Soporte Inicial | C15: Atención a bugs durante la puesta en marcha | D15: QA | E15: 5 | F15: =IF(D15="Alberto", Configuración!$B$5, IF(D15="Junior", Configuración!$B$7, IF(D15="QA", Configuración!$B$8, 0))) | G15: =E15*F15 | H15: ='Overhead y Capacidad'!$B$27 | I15: =E15*H15
A17: 2. CONSOLIDADO DE COSTOS (Resumen Técnico)
A18: Elemento de Costo | B18: Valor Calculado | C18: Unidad | D18: Referencia / Lógica
A19: Total Horas de Ingeniería del WBS | B19: =SUM(E6:E15) | C19: Horas | D19: Esfuerzo neto estimado de todo el equipo
A20: Total Mano de Obra Directa (MOD) | B20: =SUM(G6:G15) | C20: Soles (PEN) | D20: Costo directo por desarrollo de software
A21: Total Costo Indirecto de Operación (CIF) | B21: =SUM(I6:I15) | C21: Soles (PEN) | D21: Financiamiento prorrateado del overhead mensual (TACI × horas)
A22: Materiales e Infraestructura Directos (MID) | B22: 18.75 | C22: Soles (PEN) | D22: Tokens de IA para pruebas y licencias directas (Celda amarilla editable)
A23: Costo Técnico de Producción | B23: =B20+B21+B22 | C23: Soles (PEN) | D23: MOD + CIF + MID
A24: Reserva de Contingencia (20% PMBOK) | B24: =B23*Configuración!$B$18 | C24: Soles (PEN) | D24: Fondo de contingencia para mitigar riesgos y alucinaciones
A25: Costo Unitario Total (Break-Even Real) | B25: =B23+B24 | C25: Soles (PEN) | D25: Costo total de ruptura. Cobrar menos es pérdida líquida
A26: Precio Mínimo de Seguridad (Margen 20%) | B26: =B25/(1-0.20) | C26: Soles (PEN) | D26: Costo Unitario / 0.8 (Garantiza 20% utilidad neta)
A27: Precio de Venta Sugerido (Margen 40%) | B27: =B25/(1-Configuración!$B$19) | C27: Soles (PEN) | D27: Costo Unitario / 0.6 (Margen objetivo del 40%)
A29: 3. LIQUIDACIÓN COMERCIAL, IMPUESTOS Y PASARELAS
A30: Elemento de Costo | B30: Valor Calculado | C30: Unidad | D30: Referencia / Lógica
A31: Ubicación del Cliente (PE = Perú / INT = Internacional) | B31: PE | C31: Código | D31: Celda amarilla editable (PE / INT)
A32: Canal de Pago (PP = PayPal / WB = Wise / TR = Local) | B32: PP | C32: Código | D32: Celda amarilla editable (PP / WB / TR)
A33: Precio Sugerido con Gross-Up | B33: =IF(B32="PP", (B27+Configuración!$B$15*Configuración!$B$9)/(1-Configuración!$B$16), IF(B32="WB", B27/(1-Configuración!$B$17), B27)) | C33: Soles (PEN) | D33: Amortiza las comisiones financieras de retiro internacional
A34: Tasa de IGV | B34: =IF(B31="PE", Configuración!$B$12, 0.0) | C34: Porcentaje | D34: 18% si es de Perú, 0% si es exportación moderna
A35: Monto de IGV | B35: =B33*B34 | C35: Soles (PEN) | D35: IGV local cobrado al cliente
A36: Total Facturado Proforma (Con IGV) | B36: =B33+B35 | C36: Soles (PEN) | D36: Total final a facturar en el comprobante electrónico
A37: Detracción Retenida (12% SPOT) | B37: =IF(AND(B31="PE", B36>700), B36*Configuración!$B$11, 0.0) | C37: Soles (PEN) | D37: 12% retenido por cliente local y depositado en Banco de la Nación
A38: Pago a Cuenta RMT Mensual (1% SUNAT) | B38: =B33*Configuración!$B$13 | C38: Soles (PEN) | D38: Impuesto mensual a pagar a cuenta (Régimen MYPE)
A39: Provisión RMT Impuesto Anual (10% RMT) | B39: =IF((B33-B25)>0, (B33-B25)*Configuración!$B$14, 0.0) | C39: Soles (PEN) | D39: Reserva del 10% sobre la utilidad para la declaración anual
A40: Comisión Pasarela / Fricción (PayPal/Ligo) | B40: =B33-B27 | C40: Soles (PEN) | D40: Costo real descontado por pasarelas financieras
A41: Monto Neto Disponible (Flujo de Caja Real) | B41: =B36-B37-B38-B39-B40 | C41: Soles (PEN) | D41: Liquidez neta disponible tras pagar impuestos y pasarelas

Sheet ACU de Servicios
A1: ANÁLISIS DE COSTOS UNITARIOS (ACU) - SERVICIOS BASE
A2: Cálculos estructurados mediante el modelo TDABC para el portafolio de 13 servicios.
A4: ID | B4: Nombre del Servicio | C4: Categoría | D4: Hrs Alberto | E4: Hrs Junior | F4: Hrs QA | G4: Materiales (PEN) | H4: MOD (PEN) | I4: MID (PEN) | J4: CIF/Overhead (PEN) | K4: Break-Even (PEN) | L4: P. Seguridad (PEN) | M4: Venta Sugerida (PEN)
A5: C.1 | B5: Migración Zapier a n8n | C5: Automatización | D5: 3 | E5: 6 | F5: 0 | G5: 20.74 | H5: =(D5*Configuración!$B$5)+(E5*Configuración!$B$7)+(F5*Configuración!$B$8) | I5: =G5 | J5: =(D5+E5+F5)*'Overhead y Capacidad'!$B$27 | K5: =(H5+I5+J5)*(1+0.085) | L5: =K5/(1-Configuración!$B$18) | M5: =K5/(1-Configuración!$B$19)
A6: C.2.A | B6: Automatización Simple (3 Apps) | C6: Automatización | D6: 1 | E6: 3 | F6: 0 | G6: 0 | H6: =(D6*Configuración!$B$5)+(E6*Configuración!$B$7)+(F6*Configuración!$B$8) | I6: =G6 | J6: =(D6+E6+F6)*'Overhead y Capacidad'!$B$27 | K6: =(H6+I6+J6)*(1+0.085) | L6: =K6/(1-Configuración!$B$18) | M6: =K6/(1-Configuración!$B$19)
A7: B.1 | B7: Silhouette OS Lead Triage | C7: Automatización / IA | D7: 10 | E7: 15 | F7: 3 | G7: 95.63 | H7: =(D7*Configuración!$B$5)+(E7*Configuración!$B$7)+(F7*Configuración!$B$8) | I7: =G7 | J7: =(D7+E7+F7)*'Overhead y Capacidad'!$B$27 | K7: =(H7+I7+J7)*(1+0.085) | L7: =K7/(1-Configuración!$B$18) | M7: =K7/(1-Configuración!$B$19)
A8: A.1 | B8: LangGraph Swarms & Memory | C8: IA / Deep Tech | D8: 25 | E8: 25 | F8: 5 | G8: 56.25 | H8: =(D8*Configuración!$B$5)+(E8*Configuración!$B$7)+(F8*Configuración!$B$8) | I8: =G8 | J8: =(D8+E8+F8)*'Overhead y Capacidad'!$B$27 | K8: =(H8+I8+J8)*(1+0.085) | L8: =K8/(1-Configuración!$B$18) | M8: =K8/(1-Configuración!$B$19)
A9: C.2.B | B9: WordPress Web / LMS / Shop | C9: Desarrollo Web | D9: 3 | E9: 10 | F9: 1 | G9: 470.63 | H9: =(D9*Configuración!$B$5)+(E9*Configuración!$B$7)+(F9*Configuración!$B$8) | I9: =G9 | J9: =(D9+E9+F9)*'Overhead y Capacidad'!$B$27 | K9: =(H9+I9+J9)*(1+0.085) | L9: =K9/(1-Configuración!$B$18) | M9: =K9/(1-Configuración!$B$19)
A10: C.2.C | B10: Web Corporativa / Landing | C10: Desarrollo Web | D10: 2 | E10: 6 | F10: 0 | G10: 150 | H10: =(D10*Configuración!$B$5)+(E10*Configuración!$B$7)+(F10*Configuración!$B$8) | I10: =G10 | J10: =(D10+E10+F10)*'Overhead y Capacidad'!$B$27 | K10: =(H10+I10+J10)*(1+0.085) | L10: =K10/(1-Configuración!$B$18) | M10: =K10/(1-Configuración!$B$19)
A11: B.2 | B11: App Web React/TS (SPA) | C11: Desarrollo Web | D11: 10 | E11: 20 | F11: 4 | G11: 76.88 | H11: =(D11*Configuración!$B$5)+(E11*Configuración!$B$7)+(F11*Configuración!$B$8) | I11: =G11 | J11: =(D11+E11+F11)*'Overhead y Capacidad'!$B$27 | K11: =(H11+I11+J11)*(1+0.085) | L11: =K11/(1-Configuración!$B$18) | M11: =K11/(1-Configuración!$B$19)
A12: RET.B | B12: Mantenimiento Básico (SLA) | C12: Mantenimiento | D12: 1 | E12: 2 | F12: 0 | G12: 11.25 | H12: =(D12*Configuración!$B$5)+(E12*Configuración!$B$7)+(F12*Configuración!$B$8) | I12: =G12 | J12: =60.00 | K12: =(H12+I12+J12)*(1+0.085) | L12: =K12/(1-Configuración!$B$18) | M12: =K12/(1-Configuración!$B$19)
A13: RET.A | B13: Mantenimiento IA/SaaS (Adv) | C13: Mantenimiento | D13: 2 | E13: 3 | F13: 0 | G13: 37.5 | H13: =(D13*Configuración!$B$5)+(E13*Configuración!$B$7)+(F13*Configuración!$B$8) | I13: =G13 | J13: =120.00 | K13: =(H13+I13+J13)*(1+0.085) | L13: =K13/(1-Configuración!$B$18) | M13: =K13/(1-Configuración!$B$19)
A14: A.2 | B14: SaaS Completo Next.js / Stripe | C14: Software Corp | D14: 25 | E14: 40 | F14: 8 | G14: 206.25 | H14: =(D14*Configuración!$B$5)+(E14*Configuración!$B$7)+(F14*Configuración!$B$8) | I14: =G14 | J14: =(D14+E14+F14)*'Overhead y Capacidad'!$B$27 | K14: =(H14+I14+J14)*(1+0.085) | L14: =K14/(1-Configuración!$B$18) | M14: =K14/(1-Configuración!$B$19)
A15: B.2.B | B15: Software Corp Custom (ERP/CRM) | C15: Software Corp | D15: 20 | E15: 30 | F15: 6 | G15: 131.25 | H15: =(D15*Configuración!$B$5)+(E15*Configuración!$B$7)+(F15*Configuración!$B$8) | I15: =G15 | J15: =(D15+E15+F15)*'Overhead y Capacidad'!$B$27 | K15: =(H15+I15+J15)*(1+0.085) | L15: =K15/(1-Configuración!$B$18) | M15: =K15/(1-Configuración!$B$19)
A16: B.2.C | B16: Onboarding CRM HubSpot | C16: Implementación | D16: 4 | E16: 6 | F16: 0 | G16: 0 | H16: =(D16*Configuración!$B$5)+(E16*Configuración!$B$7)+(F16*Configuración!$B$8) | I16: =G16 | J16: =(D16+E16+F16)*'Overhead y Capacidad'!$B$27 | K16: =(H16+I16+J16)*(1+0.085) | L16: =K16/(1-Configuración!$B$18) | M16: =K16/(1-Configuración!$B$19)
A17: CON.1 | B17: Consultoría IA & Prompts | C17: Consultoría | D17: 5 | E17: 0 | F17: 0 | G17: 0 | H17: =(D17*Configuración!$B$5)+(E17*Configuración!$B$7)+(F17*Configuración!$B$8) | I17: =G17 | J17: =(D17+E17+F17)*'Overhead y Capacidad'!$B$27 | K17: =(H17+I17+J17)*(1+0.085) | L17: =K17/(1-Configuración!$B$18) | M17: =K17/(1-Configuración!$B$19)

Sheet ACU de Adicionales
A1: ANÁLISIS DE COSTOS UNITARIOS (ACU) - EXTRAS Y ADICIONALES
A2: Cálculos de costos base y precios de seguridad para módulos y mejoras.
A4: ID | B4: Nombre del Servicio | C4: Categoría | D4: Hrs Alberto | E4: Hrs Junior | F4: Hrs QA | G4: Materiales (PEN) | H4: MOD (PEN) | I4: MID (PEN) | J4: CIF/Overhead (PEN) | K4: Break-Even (PEN) | L4: P. Seguridad (PEN) | M4: Venta Sugerida (PEN)
A5: EX-1 | B5: Idioma Adicional (Multilenguaje) | C5: Módulo extra | D5: 1 | E5: 2 | F5: 0 | G5: 7.5 | H5: =(D5*Configuración!$B$5)+(E5*Configuración!$B$7)+(F5*Configuración!$B$8) | I5: =G5 | J5: =(D5+E5+F5)*'Overhead y Capacidad'!$B$27 | K5: =(H5+I5+J5)*(1+0.085) | L5: =K5/(1-Configuración!$B$18) | M5: =K5/(1-Configuración!$B$19)
A6: EX-2 | B6: Conexión a Pasarela Local | C6: Integración | D6: 1 | E6: 4 | F6: 0 | G6: 0 | H6: =(D6*Configuración!$B$5)+(E6*Configuración!$B$7)+(F6*Configuración!$B$8) | I6: =G6 | J6: =(D6+E6+F6)*'Overhead y Capacidad'!$B$27 | K6: =(H6+I6+J6)*(1+0.085) | L6: =K6/(1-Configuración!$B$18) | M6: =K6/(1-Configuración!$B$19)
A7: EX-3 | B7: Módulo de WhatsApp / Meta Extra | C7: Canal Extra | D7: 1 | E7: 2 | F7: 0 | G7: 15 | H7: =(D7*Configuración!$B$5)+(E7*Configuración!$B$7)+(F7*Configuración!$B$8) | I7: =G7 | J7: =(D7+E7+F7)*'Overhead y Capacidad'!$B$27 | K7: =(H7+I7+J7)*(1+0.085) | L7: =K7/(1-Configuración!$B$18) | M7: =K7/(1-Configuración!$B$19)
A8: EX-4 | B8: Flujo Extra de n8n | C8: Automatización | D8: 1 | E8: 2 | F8: 0 | G8: 0 | H8: =(D8*Configuración!$B$5)+(E8*Configuración!$B$7)+(F8*Configuración!$B$8) | I8: =G8 | J8: =(D8+E8+F8)*'Overhead y Capacidad'!$B$27 | K8: =(H8+I8+J8)*(1+0.085) | L8: =K8/(1-Configuración!$B$18) | M8: =K8/(1-Configuración!$B$19)
A9: EX-5 | B9: Optimización de Velocidad (WPO) | C9: Mejora | D9: 1 | E9: 4 | F9: 0 | G9: 75 | H9: =(D9*Configuración!$B$5)+(E9*Configuración!$B$7)+(F9*Configuración!$B$8) | I9: =G9 | J9: =(D9+E9+F9)*'Overhead y Capacidad'!$B$27 | K9: =(H9+I9+J9)*(1+0.085) | L9: =K9/(1-Configuración!$B$18) | M9: =K9/(1-Configuración!$B$19)
A10: EX-6 | B10: Panel de Reportes Analíticos con IA | C10: Módulo extra | D10: 5 | E10: 10 | F10: 2 | G10: 37.5 | H10: =(D10*Configuración!$B$5)+(E10*Configuración!$B$7)+(F10*Configuración!$B$8) | I10: =G10 | J10: =(D10+E10+F10)*'Overhead y Capacidad'!$B$27 | K10: =(H10+I10+J10)*(1+0.085) | L10: =K10/(1-Configuración!$B$18) | M10: =K10/(1-Configuración!$B$19)
A11: EX-7 | B11: Capacitación Técnica Extra | C11: Soporte | D11: 1 | E11: 0 | F11: 0 | G11: 0 | H11: =(D11*Configuración!$B$5)+(E11*Configuración!$B$7)+(F11*Configuración!$B$8) | I11: =G11 | J11: =(D11+E11+F11)*'Overhead y Capacidad'!$B$27 | K11: =(H11+I11+J11)*(1+0.085) | L11: =K11/(1-Configuración!$B$18) | M11: =K11/(1-Configuración!$B$19)
A12: EX-8 | B12: Dominio y SSL Setup | C12: Infraestructura | D12: 0 | E12: 1 | F12: 0 | G12: 0 | H12: =(D12*Configuración!$B$5)+(E12*Configuración!$B$7)+(F12*Configuración!$B$8) | I12: =G12 | J12: =(D12+E12+F12)*'Overhead y Capacidad'!$B$27 | K12: =(H12+I12+J12)*(1+0.085) | L12: =K12/(1-Configuración!$B$18) | M12: =K12/(1-Configuración!$B$19)

Sheet Catálogo Comercial
A1: CATÁLOGO DE SERVICIOS Y TARIFARIO COMERCIAL
A2: Resumen consolidado para impresión o cotización directa a clientes (PEN).
A4: Código | B4: Servicio / Módulo | C4: Categoría | D4: Costo Break-Even | E4: Precio Seguridad | F4: Precio Sugerido | G4: Público Objetivo
A5: C.1 | B5: ='ACU de Servicios'!B5 | C5: ='ACU de Servicios'!C5 | D5: ='ACU de Servicios'!K5 | E5: ='ACU de Servicios'!L5 | F5: ='ACU de Servicios'!M5 | G5: Público C - Pymes
A6: C.2.A | B6: ='ACU de Servicios'!B6 | C6: ='ACU de Servicios'!C6 | D6: ='ACU de Servicios'!K6 | E6: ='ACU de Servicios'!L6 | F6: ='ACU de Servicios'!M6 | G6: Público C - Pymes
A7: B.1 | B7: ='ACU de Servicios'!B7 | C7: ='ACU de Servicios'!C7 | D7: ='ACU de Servicios'!K7 | E7: ='ACU de Servicios'!L7 | F7: ='ACU de Servicios'!M7 | G7: Público B - Agencias / Startups
A8: A.1 | B8: ='ACU de Servicios'!B8 | C8: ='ACU de Servicios'!C8 | D8: ='ACU de Servicios'!K8 | E8: ='ACU de Servicios'!L8 | F8: ='ACU de Servicios'!M8 | G8: Público A - Scale-ups / Corp
A9: C.2.B | B9: ='ACU de Servicios'!B9 | C9: ='ACU de Servicios'!C9 | D9: ='ACU de Servicios'!K9 | E9: ='ACU de Servicios'!L9 | F9: ='ACU de Servicios'!M9 | G9: Público C - E-Commerce / LMS
A10: C.2.C | B10: ='ACU de Servicios'!B10 | C10: ='ACU de Servicios'!C10 | D10: ='ACU de Servicios'!K10 | E10: ='ACU de Servicios'!L10 | F10: ='ACU de Servicios'!M10 | G10: Público C - Landing / Pymes
A11: B.2 | B11: ='ACU de Servicios'!B11 | C11: ='ACU de Servicios'!C11 | D11: ='ACU de Servicios'!K11 | E11: ='ACU de Servicios'!L11 | F11: ='ACU de Servicios'!M11 | G11: Público B - App Web React
A12: RET.B | B12: ='ACU de Servicios'!B12 | C12: ='ACU de Servicios'!C12 | D12: ='ACU de Servicios'!K12 | E12: ='ACU de Servicios'!L12 | F12: ='ACU de Servicios'!M12 | G12: Público C/B - Soporte SLA mensual
A13: RET.A | B13: ='ACU de Servicios'!B13 | C13: ='ACU de Servicios'!C13 | D13: ='ACU de Servicios'!K13 | E13: ='ACU de Servicios'!L13 | F13: ='ACU de Servicios'!M13 | G13: Público B/A - Soporte IA mensual
A14: A.2 | B14: ='ACU de Servicios'!B14 | C14: ='ACU de Servicios'!C14 | D14: ='ACU de Servicios'!K14 | E14: ='ACU de Servicios'!L14 | F14: ='ACU de Servicios'!M14 | G14: Público A - Plataformas SaaS Next.js
A15: B.2.B | B15: ='ACU de Servicios'!B15 | C15: ='ACU de Servicios'!C15 | D15: ='ACU de Servicios'!K15 | E15: ='ACU de Servicios'!L15 | F15: ='ACU de Servicios'!M15 | G15: Público B - Software Corp ERP
A16: B.2.C | B16: ='ACU de Servicios'!B16 | C16: ='ACU de Servicios'!C16 | D16: ='ACU de Servicios'!K16 | E16: ='ACU de Servicios'!L16 | F16: ='ACU de Servicios'!M16 | G16: Público B - Onboarding CRM
A17: CON.1 | B17: ='ACU de Servicios'!B17 | C17: ='ACU de Servicios'!C17 | D17: ='ACU de Servicios'!K17 | E17: ='ACU de Servicios'!L17 | F17: ='ACU de Servicios'!M17 | G17: Público B/A - Consultoría IA
A18: EX-1 | B18: ='ACU de Adicionales'!B5 | C18: ='ACU de Adicionales'!C5 | D18: ='ACU de Adicionales'!K5 | E18: ='ACU de Adicionales'!L5 | F18: ='ACU de Adicionales'!M5 | G18: Módulo Adicional Multilenguaje
A19: EX-2 | B19: ='ACU de Adicionales'!B6 | C19: ='ACU de Adicionales'!C6 | D19: ='ACU de Adicionales'!K6 | E19: ='ACU de Adicionales'!L6 | F19: ='ACU de Adicionales'!M6 | G19: Pasarela Local (Culqi/Niubiz)
A20: EX-3 | B20: ='ACU de Adicionales'!B7 | C20: ='ACU de Adicionales'!C7 | D20: ='ACU de Adicionales'!K7 | E20: ='ACU de Adicionales'!L7 | F20: ='ACU de Adicionales'!M7 | G20: Meta WhatsApp API Módulo Extra
A21: EX-4 | B21: ='ACU de Adicionales'!B8 | C21: ='ACU de Adicionales'!C8 | D21: ='ACU de Adicionales'!K8 | E21: ='ACU de Adicionales'!L8 | F21: ='ACU de Adicionales'!M8 | G21: Flujo Automatización Extra n8n
A22: EX-5 | B22: ='ACU de Adicionales'!B9 | C22: ='ACU de Adicionales'!C9 | D22: ='ACU de Adicionales'!K9 | E22: ='ACU de Adicionales'!L9 | F22: ='ACU de Adicionales'!M9 | G22: Optimización de Carga WPO Web
A23: EX-6 | B23: ='ACU de Adicionales'!B10 | C23: ='ACU de Adicionales'!C10 | D23: ='ACU de Adicionales'!K10 | E23: ='ACU de Adicionales'!L10 | F23: ='ACU de Adicionales'!M10 | G23: Dashboard Analítico en Silhouette OS
A24: EX-7 | B24: ='ACU de Adicionales'!B11 | C24: ='ACU de Adicionales'!C11 | D24: ='ACU de Adicionales'!K11 | E24: ='ACU de Adicionales'!L11 | F24: ='ACU de Adicionales'!M11 | G24: Capacitación a Personal Técnico / hora
A25: EX-8 | B25: ='ACU de Adicionales'!B12 | C25: ='ACU de Adicionales'!C12 | D25: ='ACU de Adicionales'!K12 | E25: ='ACU de Adicionales'!L12 | F25: ='ACU de Adicionales'!M12 | G25: Registro de Dominio y SSL Setup

Sheet Simulador de Caja
A1: SIMULADOR DE FLUJO DE CAJA ANUAL PROYECTADO
A2: Modifica el número de proyectos vendidos al mes (celdas amarillas) para proyectar tu flujo de caja real anual bajo el RMT.
A4: Mes | B4: Proy. C (C.1) | C4: Proy. B (B.1) | D4: Proy. A (A.1) | E4: Retainers (RET.B) | F4: Ingresos Brutos (S/.) | G4: Overhead Fijo (S/.) | H4: Nómina Apoyo (S/.) | I4: Impuesto RMT (1%) (S/.) | J4: Comisiones (8.5%) (S/.) | K4: Provisión Renta (10%) (S/.) | L4: Flujo Disponible (S/.)
A5: Enero | B5: 0 | C5: 0 | D5: 0 | E5: 2 | F5: =(B5*'Catálogo Comercial'!$F$5)+(C5*'Catálogo Comercial'!$F$7)+(D5*'Catálogo Comercial'!$F$8)+(E5*'Catálogo Comercial'!$F$12) | G5: ='Overhead y Capacidad'!$B$26 | H5: =(B5*180.00)+(C5*517.50)+(D5*862.50)+(E5*60.00) | I5: =F5*Configuración!$B$13 | J5: =F5*0.085 | K5: =IF((F5-G5-H5-J5)>0, (F5-G5-H5-J5)*Configuración!$B$14, 0.0) | L5: =F5-G5-H5-I5-J5-K5
A6: Febrero | B6: 1 | C6: 1 | D6: 0 | E6: 2 | F6: =(B6*'Catálogo Comercial'!$F$5)+(C6*'Catálogo Comercial'!$F$7)+(D6*'Catálogo Comercial'!$F$8)+(E6*'Catálogo Comercial'!$F$12) | G6: ='Overhead y Capacidad'!$B$26 | H6: =(B6*180.00)+(C6*517.50)+(D6*862.50)+(E6*60.00) | I6: =F6*Configuración!$B$13 | J6: =F6*0.085 | K6: =IF((F6-G6-H6-J6)>0, (F6-G6-H6-J6)*Configuración!$B$14, 0.0) | L6: =F6-G6-H6-I6-J6-K6
A7: Marzo | B7: 0 | C7: 0 | D7: 0 | E7: 2 | F7: =(B7*'Catálogo Comercial'!$F$5)+(C7*'Catálogo Comercial'!$F$7)+(D7*'Catálogo Comercial'!$F$8)+(E7*'Catálogo Comercial'!$F$12) | G7: ='Overhead y Capacidad'!$B$26 | H7: =(B7*180.00)+(C7*517.50)+(D7*862.50)+(E7*60.00) | I7: =F7*Configuración!$B$13 | J7: =F7*0.085 | K7: =IF((F7-G7-H7-J7)>0, (F7-G7-H7-J7)*Configuración!$B$14, 0.0) | L7: =F7-G7-H7-I7-J7-K7
A8: Abril | B8: 1 | C8: 0 | D8: 1 | E8: 4 | F8: =(B8*'Catálogo Comercial'!$F$5)+(C8*'Catálogo Comercial'!$F$7)+(D8*'Catálogo Comercial'!$F$8)+(E8*'Catálogo Comercial'!$F$12) | G8: ='Overhead y Capacidad'!$B$26 | H8: =(B8*180.00)+(C8*517.50)+(D8*862.50)+(E8*60.00) | I8: =F8*Configuración!$B$13 | J8: =F8*0.085 | K8: =IF((F8-G8-H8-J8)>0, (F8-G8-H8-J8)*Configuración!$B$14, 0.0) | L8: =F8-G8-H8-I8-J8-K8
A9: Mayo | B9: 0 | C9: 1 | D9: 0 | E9: 4 | F9: =(B9*'Catálogo Comercial'!$F$5)+(C9*'Catálogo Comercial'!$F$7)+(D9*'Catálogo Comercial'!$F$8)+(E9*'Catálogo Comercial'!$F$12) | G9: ='Overhead y Capacidad'!$B$26 | H9: =(B9*180.00)+(C9*517.50)+(D9*862.50)+(E9*60.00) | I9: =F9*Configuración!$B$13 | J9: =F9*0.085 | K9: =IF((F9-G9-H9-J9)>0, (F9-G9-H9-J9)*Configuración!$B$14, 0.0) | L9: =F9-G9-H9-I9-J9-K9
A10: Junio | B10: 1 | C10: 0 | D10: 0 | E10: 4 | F10: =(B10*'Catálogo Comercial'!$F$5)+(C10*'Catálogo Comercial'!$F$7)+(D10*'Catálogo Comercial'!$F$8)+(E10*'Catálogo Comercial'!$F$12) | G10: ='Overhead y Capacidad'!$B$26 | H10: =(B10*180.00)+(C10*517.50)+(D10*862.50)+(E10*60.00) | I10: =F10*Configuración!$B$13 | J10: =F10*0.085 | K10: =IF((F10-G10-H10-J10)>0, (F10-G10-H10-J10)*Configuración!$B$14, 0.0) | L10: =F10-G10-H10-I10-J10-K10
A11: Julio | B11: 0 | C11: 0 | D11: 0 | E11: 4 | F11: =(B11*'Catálogo Comercial'!$F$5)+(C11*'Catálogo Comercial'!$F$7)+(D11*'Catálogo Comercial'!$F$8)+(E11*'Catálogo Comercial'!$F$12) | G11: ='Overhead y Capacidad'!$B$26 | H11: =(B11*180.00)+(C11*517.50)+(D11*862.50)+(E11*60.00) | I11: =F11*Configuración!$B$13 | J11: =F11*0.085 | K11: =IF((F11-G11-H11-J11)>0, (F11-G11-H11-J11)*Configuración!$B$14, 0.0) | L11: =F11-G11-H11-I11-J11-K11
A12: Agosto | B12: 1 | C12: 1 | D12: 0 | E12: 4 | F12: =(B12*'Catálogo Comercial'!$F$5)+(C12*'Catálogo Comercial'!$F$7)+(D12*'Catálogo Comercial'!$F$8)+(E12*'Catálogo Comercial'!$F$12) | G12: ='Overhead y Capacidad'!$B$26 | H12: =(B12*180.00)+(C12*517.50)+(D12*862.50)+(E12*60.00) | I12: =F12*Configuración!$B$13 | J12: =F12*0.085 | K12: =IF((F12-G12-H12-J12)>0, (F12-G12-H12-J12)*Configuración!$B$14, 0.0) | L12: =F12-G12-H12-I12-J12-K12
A13: Septiembre | B13: 0 | C13: 0 | D13: 0 | E13: 4 | F13: =(B13*'Catálogo Comercial'!$F$5)+(C13*'Catálogo Comercial'!$F$7)+(D13*'Catálogo Comercial'!$F$8)+(E13*'Catálogo Comercial'!$F$12) | G13: ='Overhead y Capacidad'!$B$26 | H13: =(B13*180.00)+(C13*517.50)+(D13*862.50)+(E13*60.00) | I13: =F13*Configuración!$B$13 | J13: =F13*0.085 | K13: =IF((F13-G13-H13-J13)>0, (F13-G13-H13-J13)*Configuración!$B$14, 0.0) | L13: =F13-G13-H13-I13-J13-K13
A14: Octubre | B14: 1 | C14: 0 | D14: 0 | E14: 4 | F14: =(B14*'Catálogo Comercial'!$F$5)+(C14*'Catálogo Comercial'!$F$7)+(D14*'Catálogo Comercial'!$F$8)+(E14*'Catálogo Comercial'!$F$12) | G14: ='Overhead y Capacidad'!$B$26 | H14: =(B14*180.00)+(C14*517.50)+(D14*862.50)+(E14*60.00) | I14: =F14*Configuración!$B$13 | J14: =F14*0.085 | K14: =IF((F14-G14-H14-J14)>0, (F14-G14-H14-J14)*Configuración!$B$14, 0.0) | L14: =F14-G14-H14-I14-J14-K14
A15: Noviembre | B15: 0 | C15: 1 | D15: 0 | E15: 4 | F15: =(B15*'Catálogo Comercial'!$F$5)+(C15*'Catálogo Comercial'!$F$7)+(D15*'Catálogo Comercial'!$F$8)+(E15*'Catálogo Comercial'!$F$12) | G15: ='Overhead y Capacidad'!$B$26 | H15: =(B15*180.00)+(C15*517.50)+(D15*862.50)+(E15*60.00) | I15: =F15*Configuración!$B$13 | J15: =F15*0.085 | K15: =IF((F15-G15-H15-J15)>0, (F15-G15-H15-J15)*Configuración!$B$14, 0.0) | L15: =F15-G15-H15-I15-J15-K15
A16: Diciembre | B16: 1 | C16: 0 | D16: 0 | E16: 4 | F16: =(B16*'Catálogo Comercial'!$F$5)+(C16*'Catálogo Comercial'!$F$7)+(D16*'Catálogo Comercial'!$F$8)+(E16*'Catálogo Comercial'!$F$12) | G16: ='Overhead y Capacidad'!$B$26 | H16: =(B16*180.00)+(C16*517.50)+(D16*862.50)+(E16*60.00) | I16: =F16*Configuración!$B$13 | J16: =F16*0.085 | K16: =IF((F16-G16-H16-J16)>0, (F16-G16-H16-J16)*Configuración!$B$14, 0.0) | L16: =F16-G16-H16-I16-J16-K16
A17: TOTAL ANUAL | B17: =SUM(B5:B16) | C17: =SUM(C5:C16) | D17: =SUM(D5:D16) | E17: =SUM(E5:E16) | F17: =SUM(F5:F16) | G17: =SUM(G5:G16) | H17: =SUM(H5:H16) | I17: =SUM(I5:I16) | ... L17: =SUM(L5:L16)
